alu-main/full_adder.v
module full_adder(S, Cout, A, B, Cin);
    input A, B, Cin;
    output S, Cout;
    wire w1, w2, w3;

    // syntax: gate instance_name(output, input_1, input_2...)
    xor Sresult(S, A, B, Cin);
    and A_and_B(w1, A, B);
    and A_and_C(w2, A, Cin);
    and B_and_C(w3, B, Cin);
    or (Cout, w1, w2, w3);

endmodule

// iverilog -o full_adder -s full_adder_tb .\full_adder.v .\full_adder_tb.v
// vvp .\full_adder

alu-main/or_1.v
module or_1(out, in1, in2);
    input in1, in2;
    output out;

    // syntax: gate instance_name(output, input_1, input_2...)
    or in1_and_in2(out, in1, in2);

endmodule

// iverilog -o or_1 -s or_1_tb .\or_1.v .\or_1_tb.v
// vvp .\or_1

alu-main/logic/and_1.v
module and_1(out, in1, in2);
    input in1, in2;
    output out;

    // syntax: gate instance_name(output, input_1, input_2...)
    and in1_and_in2(out, in1, in2);

endmodule

// iverilog -o and_1 -s and_1_tb .\and_1.v .\and_1_tb.v
// vvp .\and_1

alu-main/cla_8.v
module cla_8 (
    input [7:0] A,
    input [7:0] B,
    input Cin,
    output [7:0] Sum,
    output Cout,
    output Pout, // Propagate output for higher-level CLA
    output Gout  // Generate output for higher-level CLA
);
    wire [7:0] P, G;
    wire [7:0] C;
    wire [27:0] term; 

    // need generate fns
    and_1 g0_gate(.out(G[0]), .in1(A[0]), .in2(B[0]));
    and_1 g1_gate(.out(G[1]), .in1(A[1]), .in2(B[1]));
    and_1 g2_gate(.out(G[2]), .in1(A[2]), .in2(B[2]));
    and_1 g3_gate(.out(G[3]), .in1(A[3]), .in2(B[3]));
    and_1 g4_gate(.out(G[4]), .in1(A[4]), .in2(B[4]));
    and_1 g5_gate(.out(G[5]), .in1(A[5]), .in2(B[5]));
    and_1 g6_gate(.out(G[6]), .in1(A[6]), .in2(B[6]));
    and_1 g7_gate(.out(G[7]), .in1(A[7]), .in2(B[7]));

    // need propagation fns
    or_1 p0_gate(.out(P[0]), .in1(A[0]), .in2(B[0]));
    or_1 p1_gate(.out(P[1]), .in1(A[1]), .in2(B[1]));
    or_1 p2_gate(.out(P[2]), .in1(A[2]), .in2(B[2]));
    or_1 p3_gate(.out(P[3]), .in1(A[3]), .in2(B[3]));
    or_1 p4_gate(.out(P[4]), .in1(A[4]), .in2(B[4]));
    or_1 p5_gate(.out(P[5]), .in1(A[5]), .in2(B[5]));
    or_1 p6_gate(.out(P[6]), .in1(A[6]), .in2(B[6]));
    or_1 p7_gate(.out(P[7]), .in1(A[7]), .in2(B[7]));

    //////// Carry terms (prop and gen components)
    // C0 = Cin
    assign C[0] = Cin;
    assign Cout = C[7];

    // generally c_i+1 = g_i + (p_i & c_i)
    // for each c_i below, we will make each OR term its own wire

    //             t_0
    // c_1 = g_0 + p_0 & c_0
    and (term[0], P[0], C[0]);
    or (C[1], G[0], term[0]);

    //                                t_1           t_2 = p_1 & t_0
    // c_2 = g_1 + p_1 & c_1  = g_1 + (p_1 & g_0) + (p_1 & p_0 & c_0)
    and (term[1], P[1], G[0]);
    and (term[2], P[1], P[0], C[0]);
    or (C[2], G[1], term[1], term[2]);

    //                                t_3           t_4 = p_2 & t_1     t_5 = p_2 & t_2
    // c_3 = g_2 + p_2 & c_2  = g_2 + (p_2 & g_1) + (p_2 & p_1 & g_0) + (p_2 & p_1 & p_0 & c_0)
    and (term[3], P[2], G[1]);
    and (term[4], P[2], P[1], G[0]);
    and (term[5], P[2], P[1], P[0], C[0]);
    or (C[3], G[2], term[3], term[4], term[5]);

    //                                t_9           t_10 = p_3 & t_4    t_11 = p_3 & t_5          t_12 = p_3 & t_6
    // c_4 = g_3 + p_3 & c_3  = g_3 + (p_3 & g_2) + (p_3 & p_2 & g_1) + (p_3 & p_2 & p_1 & g_0) + (p_3 & p_2 & p_1 & p_0 & c_0)
    and (term[6], P[3], G[2]);
    and (term[7], P[3], P[2], G[1]);
    and (term[8], P[3], P[2], P[1], G[0]);
    and (term[9], P[3], P[2], P[1], P[0], C[0]);
    or (C[4], G[3], term[6], term[7], term[8], term[9]);

    //                                      t_16          t_17 = p_4 & t_9    t_18 = p_4 & t_10         t_19 = p_4 & t_11               t_20 = p_4 & t_12
    // c_5 = g_4 + p_4 & c_4  = c_5 = g_4 + (p_4 & g_3) + (p_4 & p_3 & g_2) + (p_4 & p_3 & p_2 & g_1) + (p_4 & p_3 & p_2 & p_1 & g_0) + (p_4 & p_3 & p_2 & p_1 & p_0 & c_0)
    and (term[10], P[4], G[3]);
    and (term[11], P[4], P[3], G[2]);
    and (term[12], P[4], P[3], P[2], G[1]);
    and (term[13], P[4], P[3], P[2], P[1], G[0]);
    and (term[14], P[4], P[3], P[2], P[1], P[0], C[0]);
    or (C[5], G[4], term[10], term[11], term[12], term[13], term[14]);
    

    //                                      t_25          t_26 = t_16
    // c_6 = g_5 + p_5 & c_5  = c_6 = g_5 + (p_5 & g_4) + (p_5 & p_4 & g_3) + (p_5 & p_4 & p_3 & g_2) + (p_5 & p_4 & p_3 & p_2 & g_1) + (p_5 & p_4 & p_3 & p_2 & p_1 & g_0) + (p_5 & p_4 & p_3 & p_2 & p_1 & p_0 & c_0)
    and (term[15], P[5], G[4]);
    and (term[16], P[5], P[4], G[3]);
    and (term[17], P[5], P[4], P[3], G[2]);
    and (term[18], P[5], P[4], P[3], P[2], G[1]);
    and (term[19], P[5], P[4], P[3], P[2], P[1], G[0]);
    and (term[20], P[5], P[4], P[3], P[2], P[1], P[0], C[0]);
    or (C[6], G[5], term[15], term[16], term[17], term[18], term[19], term[20]);


    // c_7 = g_6 + p_6 & c_6  = c_7 = g_6 + (p_6 & g_5) + (p_6 & p_5 & g_4) + (p_6 & p_5 & p_4 & g_3) + (p_6 & p_5 & p_4 & p_3 & g_2) + (p_6 & p_5 & p_4 & p_3 & p_2 & g_1) + (p_6 & p_5 & p_4 & p_3 & p_2 & p_1 & g_0) + (p_6 & p_5 & p_4 & p_3 & p_2 & p_1 & p_0 & c_0)
    and (term[21], P[6], G[5]);
    and (term[22], P[6], P[5], G[4]);
    and (term[23], P[6], P[5], P[4], G[3]);
    and (term[24], P[6], P[5], P[4], P[3], G[2]);
    and (term[25], P[6], P[5], P[4], P[3], P[2], G[1]);
    and (term[26], P[6], P[5], P[4], P[3], P[2], P[1], G[0]);
    and (term[27], P[6], P[5], P[4], P[3], P[2], P[1], P[0], C[0]);
    or (C[7], G[6], term[21], term[22], term[23], term[24], term[25], term[26], term[27]);

    wire [7:0] unused_carry;
    //////// Sum (using carry components])
    full_adder S_0(Sum[0], unused_carry[0], A[0], B[0], C[0]);
    full_adder S_1(Sum[1], unused_carry[0], A[1], B[1], C[1]);
    full_adder S_2(Sum[2], unused_carry[2], A[2], B[2], C[2]);
    full_adder S_3(Sum[3], unused_carry[3], A[3], B[3], C[3]);
    full_adder S_4(Sum[4], unused_carry[4], A[4], B[4], C[4]);
    full_adder S_5(Sum[5], unused_carry[5], A[5], B[5], C[5]);
    full_adder S_6(Sum[6], unused_carry[6], A[6], B[6], C[6]);
    full_adder S_7(Sum[7], unused_carry[7], A[7], B[7], C[7]);

    // doesnt work
    // wire [7:0] unused_carry;
    // //////// Sum (using carry components])
    // full_adder S_0(Sum[0], C[0], A[0], B[0], Cin);
    // full_adder S_1(Sum[1], C[0], A[1], B[1], C[0]);
    // full_adder S_2(Sum[2], C[2], A[2], B[2], C[1]);
    // full_adder S_3(Sum[3], C[3], A[3], B[3], C[2]);
    // full_adder S_4(Sum[4], C[4], A[4], B[4], C[3]);
    // full_adder S_5(Sum[5], C[5], A[5], B[5], C[4]);
    // full_adder S_6(Sum[6], C[6], A[6], B[6], C[5]);
    // full_adder S_7(Sum[7], C[7], A[7], B[7], C[6]);

    assign Pout = P[7];
    assign Gout = G[7];

endmodule

// iverilog -o cla_8 -s cla_8_tb .\cla_8.v .\cla_8_tb.v .\logic\or_1.v .\logic\and_1.v .\full_adder.v
// vvp .\cla_8

alu-main/cla_8_tb.v
`timescale 1 ns / 100 ps

module cla_8_tb;
//////
// inputs to the module (reg)
    reg Cin;
    reg [7:0] A, B;
    // outputs of the module (wire)
    wire [7:0] Sum;
    wire Cout;
    // Instantiate the module to test
    cla_8 addsub(.Sum(Sum), .Cout(Cout), .A(A), .B(B), .Cin(Cin));

    //////    Input Manipulation
    initial begin


        /////////////   Addition
        Cin = 1'b0;
        A = 8'b00000101;
        B = 8'b00000111;
        #20;
        $display("A:%d, B:%d, Cin:%b => S:%d, Cout:%b", A, B, Cin, Sum, Cout);
        
        A = 8'd244;
        B = 8'd16;
        #20;
        $display("A:%d, B:%d, Cin:%b => S:%d, Cout:%b", A, B, Cin, Sum, Cout);
        
        A = 8'd25;
        B = 8'd32;
        #20;
        $display("A:%d, B:%d, Cin:%b => S:%d, Cout:%b", A, B, Cin, Sum, Cout);
        
        A = 8'b11111111;
        B = 8'd17;
        #20;
        $display("A:%d, B:%d, Cin:%b => S:%d, Cout:%b", A, B, Cin, Sum, Cout);
        
        A = 8'd3;
        B = 8'd7;
        #20;
        $display("A:%d, B:%d, Cin:%b => S:%d, Cout:%b", A, B, Cin, Sum, Cout);


        /////// Subtraction
        Cin = 1'b1;
        A = 8'b00000101;
        B = 8'b00000111;
        #20;
        $display("A:%d, B:%d, Cin:%b => S:%d, Cout:%b", A, B, Cin, Sum, Cout);
        
        A = 8'd244;
        B = 8'd16;
        #20;
        $display("A:%d, B:%d, Cin:%b => S:%d, Cout:%b", A, B, Cin, Sum, Cout);
        
        A = 8'd25;
        B = 8'd32;
        #20;
        $display("A:%d, B:%d, Cin:%b => S:%d, Cout:%b", A, B, Cin, Sum, Cout);
        
        A = 8'b11111111;
        B = 8'd17;
        #20;
        $display("A:%d, B:%d, Cin:%b => S:%d, Cout:%b", A, B, Cin, Sum, Cout);
        
        A = 8'd3;
        B = 8'd7;
        #20;
        $display("A:%d, B:%d, Cin:%b => S:%d, Cout:%b", A, B, Cin, Sum, Cout);
        
    end 

    
    // output waveform
    initial begin
        // output file name
        $dumpfile("cla_8.vcd");
        $dumpvars(0, cla_8_tb);
    end

endmodule

alu-main/cla_8.vcd
$date
	Fri Jan 31 15:03:17 2025
$end
$version
	Icarus Verilog
$end
$timescale
	100ps
$end
$scope module cla_8_tb $end
$var wire 8 ! Sum [7:0] $end
$var wire 1 " Cout $end
$var reg 8 # A [7:0] $end
$var reg 8 $ B [7:0] $end
$var reg 1 % Cin $end
$scope module addsub $end
$var wire 8 & A [7:0] $end
$var wire 8 ' B [7:0] $end
$var wire 1 % Cin $end
$var wire 8 ( unused_carry [7:0] $end
$var wire 28 ) term [27:0] $end
$var wire 8 * Sum [7:0] $end
$var wire 1 + Pout $end
$var wire 8 , P [7:0] $end
$var wire 1 - Gout $end
$var wire 8 . G [7:0] $end
$var wire 1 " Cout $end
$var wire 8 / C [7:0] $end
$scope module S_0 $end
$var wire 1 0 A $end
$var wire 1 1 B $end
$var wire 1 2 Cin $end
$var wire 1 3 Cout $end
$var wire 1 4 S $end
$var wire 1 5 w1 $end
$var wire 1 6 w2 $end
$var wire 1 7 w3 $end
$upscope $end
$scope module S_1 $end
$var wire 1 8 A $end
$var wire 1 9 B $end
$var wire 1 : Cin $end
$var wire 1 ; Cout $end
$var wire 1 < S $end
$var wire 1 = w1 $end
$var wire 1 > w2 $end
$var wire 1 ? w3 $end
$upscope $end
$scope module S_2 $end
$var wire 1 @ A $end
$var wire 1 A B $end
$var wire 1 B Cin $end
$var wire 1 C Cout $end
$var wire 1 D S $end
$var wire 1 E w1 $end
$var wire 1 F w2 $end
$var wire 1 G w3 $end
$upscope $end
$scope module S_3 $end
$var wire 1 H A $end
$var wire 1 I B $end
$var wire 1 J Cin $end
$var wire 1 K Cout $end
$var wire 1 L S $end
$var wire 1 M w1 $end
$var wire 1 N w2 $end
$var wire 1 O w3 $end
$upscope $end
$scope module S_4 $end
$var wire 1 P A $end
$var wire 1 Q B $end
$var wire 1 R Cin $end
$var wire 1 S Cout $end
$var wire 1 T S $end
$var wire 1 U w1 $end
$var wire 1 V w2 $end
$var wire 1 W w3 $end
$upscope $end
$scope module S_5 $end
$var wire 1 X A $end
$var wire 1 Y B $end
$var wire 1 Z Cin $end
$var wire 1 [ Cout $end
$var wire 1 \ S $end
$var wire 1 ] w1 $end
$var wire 1 ^ w2 $end
$var wire 1 _ w3 $end
$upscope $end
$scope module S_6 $end
$var wire 1 ` A $end
$var wire 1 a B $end
$var wire 1 b Cin $end
$var wire 1 c Cout $end
$var wire 1 d S $end
$var wire 1 e w1 $end
$var wire 1 f w2 $end
$var wire 1 g w3 $end
$upscope $end
$scope module S_7 $end
$var wire 1 h A $end
$var wire 1 i B $end
$var wire 1 j Cin $end
$var wire 1 k Cout $end
$var wire 1 l S $end
$var wire 1 m w1 $end
$var wire 1 n w2 $end
$var wire 1 o w3 $end
$upscope $end
$scope module g0_gate $end
$var wire 1 p in1 $end
$var wire 1 q in2 $end
$var wire 1 r out $end
$upscope $end
$scope module g1_gate $end
$var wire 1 s in1 $end
$var wire 1 t in2 $end
$var wire 1 u out $end
$upscope $end
$scope module g2_gate $end
$var wire 1 v in1 $end
$var wire 1 w in2 $end
$var wire 1 x out $end
$upscope $end
$scope module g3_gate $end
$var wire 1 y in1 $end
$var wire 1 z in2 $end
$var wire 1 { out $end
$upscope $end
$scope module g4_gate $end
$var wire 1 | in1 $end
$var wire 1 } in2 $end
$var wire 1 ~ out $end
$upscope $end
$scope module g5_gate $end
$var wire 1 !" in1 $end
$var wire 1 "" in2 $end
$var wire 1 #" out $end
$upscope $end
$scope module g6_gate $end
$var wire 1 $" in1 $end
$var wire 1 %" in2 $end
$var wire 1 &" out $end
$upscope $end
$scope module g7_gate $end
$var wire 1 '" in1 $end
$var wire 1 (" in2 $end
$var wire 1 )" out $end
$upscope $end
$scope module p0_gate $end
$var wire 1 *" in1 $end
$var wire 1 +" in2 $end
$var wire 1 ," out $end
$upscope $end
$scope module p1_gate $end
$var wire 1 -" in1 $end
$var wire 1 ." in2 $end
$var wire 1 /" out $end
$upscope $end
$scope module p2_gate $end
$var wire 1 0" in1 $end
$var wire 1 1" in2 $end
$var wire 1 2" out $end
$upscope $end
$scope module p3_gate $end
$var wire 1 3" in1 $end
$var wire 1 4" in2 $end
$var wire 1 5" out $end
$upscope $end
$scope module p4_gate $end
$var wire 1 6" in1 $end
$var wire 1 7" in2 $end
$var wire 1 8" out $end
$upscope $end
$scope module p5_gate $end
$var wire 1 9" in1 $end
$var wire 1 :" in2 $end
$var wire 1 ;" out $end
$upscope $end
$scope module p6_gate $end
$var wire 1 <" in1 $end
$var wire 1 =" in2 $end
$var wire 1 >" out $end
$upscope $end
$scope module p7_gate $end
$var wire 1 ?" in1 $end
$var wire 1 @" in2 $end
$var wire 1 A" out $end
$upscope $end
$upscope $end
$upscope $end
$enddefinitions $end
$comment Show the parameter values. $end
$dumpall
$end
#0
$dumpvars
0A"
0@"
0?"
0>"
0="
0<"
0;"
0:"
09"
08"
07"
06"
05"
04"
03"
12"
11"
10"
1/"
1."
0-"
1,"
1+"
1*"
0)"
0("
0'"
0&"
0%"
0$"
0#"
0""
0!"
0~
0}
0|
0{
0z
0y
1x
1w
1v
0u
1t
0s
1r
1q
1p
0o
0n
0m
0l
0k
0j
0i
0h
0g
0f
0e
0d
0c
0b
0a
0`
0_
0^
0]
0\
0[
0Z
0Y
0X
0W
0V
0U
0T
0S
0R
0Q
0P
0O
0N
0M
1L
0K
1J
0I
0H
1G
1F
1E
1D
1C
1B
1A
1@
1?
0>
0=
0<
1;
1:
19
08
07
06
15
04
13
02
11
10
b1110 /
b101 .
0-
b111 ,
0+
b1100 *
b10010 )
b1z1 (
b111 '
b101 &
0%
b111 $
b101 #
0"
b1100 !
$end
#200
1c
1k
0C
1f
1n
0F
0L
1[
1b
1j
1"
0B
0J
1^
1Z
0:
b11100000 /
b10000001000000000000000 )
0;
1+
03
b111100z0 (
1S
0x
0/"
0<
0?
1D
0E
0G
0r
b10000 .
1~
0,"
18"
1;"
1>"
b11110100 ,
1A"
05
1U
0\
0d
b100 !
b100 *
0l
0q
0t
0w
1}
0+"
0."
01"
17"
01
09
0A
1Q
0p
1|
1!"
1$"
1'"
0*"
16"
19"
1<"
1?"
00
1P
1X
1`
1h
b10000 $
b10000 '
b11110100 #
b11110100 &
#400
0[
0b
0j
0"
1\
0Z
b0 /
b0 )
0S
0+
0c
b0z0 (
0k
b0 .
0~
1T
0U
0_
1,"
02"
15"
0>"
b111001 ,
0A"
14
0D
1L
0^
0d
0f
b111001 !
b111001 *
0l
0n
0}
1""
07"
1:"
0Q
1Y
1p
0v
1y
0!"
0$"
0'"
1*"
00"
13"
09"
0<"
0?"
10
0@
1H
0X
0`
0h
b100000 $
b100000 '
b11001 #
b11001 &
#600
1c
1k
1f
1C
1K
1V
1W
1n
1[
1b
1F
0L
1N
1R
1j
1"
1;
0\
1^
1B
1J
1>
1Z
1:
b11111110 /
b100010010001010000100010010 )
13
b111111z1 (
1S
1+
1r
b10001 .
1~
04
15
1T
1U
1/"
12"
1>"
b11111111 ,
1A"
0<
0D
0d
b10000 !
b10000 *
0l
1q
1}
0""
1+"
17"
0:"
11
1Q
0Y
1s
1v
1!"
1$"
1'"
1-"
10"
19"
1<"
1?"
18
1@
1X
1`
1h
b10001 $
b10001 '
b11111111 #
b11111111 &
#800
0T
0Z
0R
0b
0j
0"
b1110 /
b11010 )
0+
0K
0S
0[
0c
b1z1 (
0k
1u
1<
1=
1?
1G
0W
b11 .
0~
05"
08"
0;"
0>"
b111 ,
0A"
0F
1L
0N
0U
0V
0\
0^
0d
0f
b1010 !
b1010 *
0l
0n
1t
1w
0}
1."
11"
07"
19
1A
0Q
0v
0y
0|
0!"
0$"
0'"
00"
03"
06"
09"
0<"
0?"
0@
0H
0P
0X
0`
0h
b111 $
b111 '
b11 #
b11 &
#1000
0u
b101 .
1x
0<
0=
0>
1D
1E
1F
b1101 !
b1101 *
14
16
17
b110111 )
0s
1v
0-"
10"
08
1@
12
b101 #
b101 &
b1111 /
1%
#1200
1c
1k
0C
1f
1n
1[
0F
0L
1b
1j
1"
1^
0:
0B
0J
1Z
b11100001 /
b10000001000000000000000 )
0;
1+
03
b111100z0 (
1S
0x
0/"
07
0<
0?
1D
0E
0G
0r
b10000 .
1~
0,"
18"
1;"
1>"
b11110100 ,
1A"
05
06
1U
0\
0d
b101 !
b101 *
0l
0q
0t
0w
1}
0+"
0."
01"
17"
01
09
0A
1Q
0p
1|
1!"
1$"
1'"
0*"
16"
19"
1<"
1?"
00
1P
1X
1`
1h
b10000 $
b10000 '
b11110100 #
b11110100 &
#1400
0[
0b
1<
0j
0"
1\
1:
0Z
b11 /
b1 )
0S
0+
13
0c
b0zx (
0k
b0 .
0~
1T
0U
0_
1,"
02"
15"
0>"
b111001 ,
0A"
04
16
0D
1L
0^
0d
0f
b111010 !
b111010 *
0l
0n
0}
1""
07"
1:"
0Q
1Y
1p
0v
1y
0!"
0$"
0'"
1*"
00"
13"
09"
0<"
0?"
10
0@
1H
0X
0`
0h
b100000 $
b100000 '
b11001 #
b11001 &
#1600
1c
1k
1f
1C
1K
1V
1W
1n
1[
1b
1F
0L
1N
1R
1j
1"
0\
1^
1B
1J
1Z
b11111111 /
b1100010110001110001100110111 )
1S
1+
b111111z1 (
1;
1r
b10001 .
1~
14
15
17
1T
1U
1/"
12"
1>"
b11111111 ,
1A"
0<
1>
0D
0d
b10001 !
b10001 *
0l
1q
1}
0""
1+"
17"
0:"
11
1Q
0Y
1s
1v
1!"
1$"
1'"
1-"
10"
19"
1<"
1?"
18
1@
1X
1`
1h
b10001 $
b10001 '
b11111111 #
b11111111 &
#1800
0T
0Z
0R
0b
0j
0"
b1111 /
b111111 )
0+
0K
0S
0[
0c
b1z1 (
0k
1u
1<
1=
1?
1G
0W
b11 .
0~
05"
08"
0;"
0>"
b111 ,
0A"
0F
1L
0N
0U
0V
0\
0^
0d
0f
b1011 !
b1011 *
0l
0n
1t
1w
0}
1."
11"
07"
19
1A
0Q
0v
0y
0|
0!"
0$"
0'"
00"
03"
06"
09"
0<"
0?"
0@
0H
0P
0X
0`
0h
b111 $
b111 '
b11 #
b11 &
