alu-main/sra_32_2b.v
module sra_32_2b (
    input [31:0] in,
    output [31:0] out
);

    // 1100101 -> 1111001
    // 0000111 -> 0000001
    assign out[31:30] = {in[31], in[31]};
    assign out[29:0] = in[31:2];
endmodule


// iverilog -o sra_32_2b -s sra_32_2b_tb -c .\sra_reqs.txt

alu-main/sra_32_2b_tb.v
`timescale 1 ns / 100 ps

module sra_32_2b_tb;
//////
// inputs to the module (reg)
    reg [31:0] in;
    wire [31:0] out;
    // outputs of the module (wire)
    
    // Instantiate the module to test
    sra_32_2b sra_32_gate(.in(in),.out(out));

    //////    Input Manipulation
    initial begin
        in = 32'd7;
        #20;
        $display("in:%b => out:%b", in, out);
        
        in = 32'd7987;
        #20;
        $display("in:%b => out:%b", in, out);
        
        in = 32'd52355257;
        #20;
        $display("in:%b => out:%b", in, out);
        
        in = 32'd120198;
        #20;
        $display("in:%b => out:%b", in, out);
        
        in = 32'd123;
        #20;
        $display("in:%b => out:%b", in, out);

        
        in = {32'b11111111000000101010101001010110};
        #20;
        $display("in:%b => out:%b", in, out);
        
        in = {32'b11111111000000101010101111110110};
        #20;
        $display("in:%b => out:%b", in, out);
        
        in = {32'b11111111000000101010101000010010};
        #20;
        $display("in:%b => out:%b", in, out);
        
        in = {32'b11111111000000101010101111010110};
        #20;
        $display("in:%b => out:%b", in, out);
        
        in = {32'b11111111000000101100101001010110};
        #20;
        $display("in:%b => out:%b", in, out);
        
    end 


    // output waveform
    initial begin
        // output file name
        $dumpfile("sra_32_2b.vcd");
        $dumpvars(0, sra_32_2b_tb);
    end

endmodule

alu-main/sra_32_2b.vcd
$date
	Fri Jan 31 23:04:49 2025
$end
$version
	Icarus Verilog
$end
$timescale
	100ps
$end
$scope module sra_32_2b_tb $end
$var wire 32 ! out [31:0] $end
$var reg 32 " in [31:0] $end
$scope module sra_32_gate $end
$var wire 32 # in [31:0] $end
$var wire 32 $ out [31:0] $end
$upscope $end
$upscope $end
$enddefinitions $end
$comment Show the parameter values. $end
$dumpall
$end
#0
$dumpvars
b1 $
b111 #
b111 "
b1 !
$end
#200
b11111001100 !
b11111001100 $
b1111100110011 "
b1111100110011 #
#400
b110001111011100000101110 !
b110001111011100000101110 $
b11000111101110000010111001 "
b11000111101110000010111001 #
#600
b111010101100001 !
b111010101100001 $
b11101010110000110 "
b11101010110000110 #
#800
b11110 !
b11110 $
b1111011 "
b1111011 #
#1000
b11111111110000001010101010010101 !
b11111111110000001010101010010101 $
b11111111000000101010101001010110 "
b11111111000000101010101001010110 #
#1200
b11111111110000001010101011111101 !
b11111111110000001010101011111101 $
b11111111000000101010101111110110 "
b11111111000000101010101111110110 #
#1400
b11111111110000001010101010000100 !
b11111111110000001010101010000100 $
b11111111000000101010101000010010 "
b11111111000000101010101000010010 #
#1600
b11111111110000001010101011110101 !
b11111111110000001010101011110101 $
b11111111000000101010101111010110 "
b11111111000000101010101111010110 #
#1800
b11111111110000001011001010010101 !
b11111111110000001011001010010101 $
b11111111000000101100101001010110 "
b11111111000000101100101001010110 #
