alu-main/lab1/full_adder.v
module full_adder(out1, out2, in1, in2, in3);
    input in1, in2, in3;
    output out1, out2;
    wire w1, w2, w3;

    // syntax: gate instance_name(output, input_1, input_2...)
    xor Sresult(out1, in1, in2, in3);
    and A_and_B(w1, in1, in2);
    and A_and_C(w2, in1, in3);
    and B_and_C(w3, in2, in3);
    or Cout(out2, w1, w2, w3);

endmodule

// iverilog -o full_adder -s full_adder_tb .\full_adder.v .\full_adder_tb.v
// vvp .\full_adder

alu-main/full_adder_tb.v
`timescale 1 ns / 100 ps

module full_adder_tb;
//////
// inputs to the module (reg)
    reg A, B, Cin;
    // outputs of the module (wire)
    wire S, Cout;
    // Instantiate the module to test
    full_adder adder(.in1(A),.in2(B),.in3(Cin),.out1(S),.out2(Cout));

    /////// Input Initialization
    // Initialize the inputs and specify the runtime
    initial begin
        // Initialize the inputs to 0
        A = 0;
        B = 0;
        Cin = 0;
        // Set a time delay, in nanoseconds
        #80;
        // Ends the testbench
        $finish;
    end

    //////    Input Manipulation
    // Toggle input A every 10 nanoseconds
    always
        #10 A = ~A;
    // Toggle input B every 20 nanoseconds
    always
        #20 B = ~B;
    // Toggle input Cin every 40 nanoseconds
    always
        #40 Cin = ~Cin;
    // Print the inputs and outputs whenever inputs change

    
    //////  Output Results   //////
    always @(A, B, Cin) begin
        // Small Delay so outputs can stabilize
        #1;
        $display("A:%b, B:%b, Cin:%b => S:%b, Cout:%b", A, B, Cin, S, Cout);

    end

    // output waveform
    initial begin
        // output file name
        $dumpfile("full_adder.vcd");
        $dumpvars(0, full_adder_tb);
    end

endmodule

lab1/full_adder.vcd
$date
	Tue Jan 14 14:54:32 2025
$end
$version
	Icarus Verilog
$end
$timescale
	100ps
$end
$scope module full_adder_tb $end
$var wire 1 ! S $end
$var wire 1 " Cout $end
$var reg 1 # A $end
$var reg 1 $ B $end
$var reg 1 % Cin $end
$scope module adder $end
$var wire 1 # in1 $end
$var wire 1 $ in2 $end
$var wire 1 % in3 $end
$var wire 1 ! out1 $end
$var wire 1 " out2 $end
$var wire 1 & w1 $end
$var wire 1 ' w2 $end
$var wire 1 ( w3 $end
$upscope $end
$upscope $end
$enddefinitions $end
$comment Show the parameter values. $end
$dumpall
$end
#0
$dumpvars
0(
0'
0&
0%
0$
0#
0"
0!
$end
#100
1!
1#
#200
0#
1$
#300
1"
0!
1&
1#
#400
0"
0&
1!
0#
0$
1%
#500
1"
0!
1'
1#
#600
0'
1(
0#
1$
#700
1!
1&
1'
1#
#800
0"
0&
0!
0'
0(
0#
0$
0%
