lab2/add_1.v

module add_1(S, Cout, A, B, Cin);
    input A, B, Cin;
    output S, Cout;
    wire w1, w2, w3, w4, w5, w6, w7, w8, w9;

    nand A_nand_B(w1, A, B);
    nand w1_nand_A(w2, w1, A);
    nand w1_nand_B(w3, w1, B);
    nand A_xor_B(w4, w2, w3);

    nand AxorB_nand_Cin(w5, w4, Cin);
    nand w5_nand_AxorB(w6, w5, w4);
    nand w5_nand_Cin(w7, w5, Cin);
    nand AxorB_xor_Cin(S, w6, w7);
    nand w_Cout(Cout, w1, w5);

endmodule


// iverilog -o add_1 -s add_1_tb .\add_1.v .\add_1_tb.v
// vvp .\add_1

alu-main/lab2/add_1_tb.v
`timescale 1 ns / 100 ps

module add_1_tb;
//////
// inputs to the module (reg)
    reg A, B, Cin;
    // outputs of the module (wire)
    wire S, Cout;
    // Instantiate the module to test
    add_1 adder(.A(A),.B(B),.Cin(Cin),.S(S),.Cout(Cout));

    /////// Input Initialization
    // Initialize the inputs and specify the runtime
    initial begin
        // Initialize the inputs to 0
        A = 0;
        B = 0;
        Cin = 0;
        // Set a time delay, in nanoseconds
        #80;
        // Ends the testbench
        $finish;
    end

    //////    Input Manipulation
    // Toggle input A every 10 nanoseconds
    always
        #10 A = ~A;
    // Toggle input B every 20 nanoseconds
    always
        #20 B = ~B;
    // Toggle input Cin every 40 nanoseconds
    always
        #40 Cin = ~Cin;
    // Print the inputs and outputs whenever inputs change

    
    //////  Output Results   //////
    always @(A, B, Cin) begin
        // Small Delay so outputs can stabilize
        #1;
        $display("A:%b, B:%b, Cin:%b => S:%b, Cout:%b", A, B, Cin, S, Cout);

    end

    // output waveform
    initial begin
        // output file name
        $dumpfile("add_1.vcd");
        $dumpvars(0, add_1_tb);
    end

endmodule

lab2/add_1.vcd
$date
	Tue Jan 21 13:24:44 2025
$end
$version
	Icarus Verilog
$end
$timescale
	100ps
$end
$scope module add_1_tb $end
$var wire 1 ! S $end
$var wire 1 " Cout $end
$var reg 1 # A $end
$var reg 1 $ B $end
$var reg 1 % Cin $end
$scope module adder $end
$var wire 1 # A $end
$var wire 1 $ B $end
$var wire 1 % Cin $end
$var wire 1 " Cout $end
$var wire 1 ! S $end
$var wire 1 & w1 $end
$var wire 1 ' w2 $end
$var wire 1 ( w3 $end
$var wire 1 ) w4 $end
$var wire 1 * w5 $end
$var wire 1 + w6 $end
$var wire 1 , w7 $end
$upscope $end
$upscope $end
$enddefinitions $end
$comment Show the parameter values. $end
$dumpall
$end
#0
$dumpvars
1,
1+
1*
0)
1(
1'
1&
0%
0$
0#
0"
0!
$end
#100
1!
0+
1)
0'
1#
#200
1'
0(
0#
1$
#300
0!
1+
0)
1(
1"
0&
1'
1#
#400
0"
1!
1&
0,
0#
0$
1%
#500
0!
1,
1"
0*
1+
1)
0'
1#
#600
1'
0(
0#
1$
#700
1!
0,
1*
0)
1(
0&
1'
1#
#800
0"
0!
1&
1,
0#
0$
0%
