alu-main/lab3/mux_2.v

module mux_2(out, select, in0, in1);
    input select;
    input in0, in1;
    output out;

    assign out = select ? in1 : in0;

endmodule

lab3/mux_4.v

module mux_4(out, select, in0, in1, in2, in3);
    input [1:0] select;
    input in0, in1, in2, in3;
    output out;
    wire w1, w2;

    mux_2 first_top(w1, select[0], in0, in1);
    mux_2 first_bottom(w2, select[0], in2, in3);
    mux_2 second(out, select[1], w1, w2);

endmodule

alu-main/lab3/mux_8.v

module mux_8(out, select, in0, in1, in2, in3, in4, in5, in6, in7);
    input [2:0] select;
    input in0, in1, in2, in3, in4, in5, in6, in7;
    output out;
    wire w1, w2;

    mux_4 first_top(w1, select[1:0], in0, in1, in2, in3);
    mux_4 first_bottom(w2, select[1:0], in4, in5, in6, in7);
    mux_2 second(out, select[2], w1, w2);

endmodule

lab3/comp_2.v


module comp_2(EQ1, GT1, A, B, EQ0, GT0);
    input EQ1, GT1;
    input [1:0] A, B;
    output EQ0, GT0;
    wire w1;

    wire [2:0] select;
    wire eqmux_out;

    assign select = {A[1], A[0], B[1]};
    // h(a1 a0 b1 b0) = B0' * f(A1, A0, B1, B0=0) + B0 * f(A1, A0, B1, B0=1)
    wire zero;
    assign zero = 1'b0;
    wire one;
    assign one = !zero;
    
    
    mux_8 eqmux(.select(select), .out(eqmux_out), .in0(!B[0]), .in1(zero), .in2(B[0]), .in3(zero), .in4(zero), .in5(!B[0]), .in6(zero), .in7(B[0]));
    and eq_out(EQ0, EQ1, !GT1, eqmux_out);


    // eq_1 = EQ1 & !GT1 & !A1 & !A0 & !B1 & !B0
    // eq_2 = EQ1 & !GT1 & !A1 & A0 & !B1 & B0
    // eq_3 = EQ1 & !GT1 & A1 & !A0 & B1 & !B0
    // eq_4 = EQ1 & !GT1 & A1 & A0 & B1 & B0

    // EQ0 = eq_1 | eq_2 | eq_3 | eq_4  = (EQ1 & !GT1) & [(!A1 & !A0 & !B1 & !B0) | (!A1 & A0 & !B1 & B0) | (A1 & !A0 & B1 & !B0) | (A1 & A0 & B1 & B0)]
    // EQ0 = (EQ1 & !GT1) & [eqmux_out]

    // A1A0B1 : logic output
    // 000 : !B0
    // 010 : B0
    // 101 : !B0
    // 111 : B0
    // the rest tied to 0.

    // gt_1 = !EQ1 & GT1
    // gt_2 = EQ1 & !GT1 & !A1 & A0 & !B1 & !B0
    // gt_3 = EQ1 & !GT1 & A1 & !B1
    // gt_4 = EQ1 & !GT1 & A1 & A0 & B1 & !B0

    // h(a1 a0 b1 b0) = B0' * f(A1, A0, B1, B0=0) + B0 * f(A1, A0, B1, B0=1)
    // A1A0B1: logic output
    // 010: !B0
    // 111: !B0
    // 1x0: 1
    //default : 0

    // 1 by default: 0 if we have (!G1 & !A1 & B1)

    // 
    wire gt_mux_out;

    mux_8 gt_mux(.select(select), .out(gt_mux_out), .in0(zero), .in1(zero), .in2(!B[0]), .in3(zero), .in4(one), .in5(zero), .in6(one), .in7(!B[0]));

    or mux_out(GT0, gt_mux_out, !EQ1 & GT1);



    // iverilog -o comp_2 -s comp_2_tb .\comp_2.v .\mux_8.v .\mux_2.v .\mux_4.v .\comp_2_tb.v
    // 
endmodule

lab3/comp_2_tb.v
`timescale 1 ns / 100 ps

module comp_2_tb;
//////
// inputs to the module (reg)
    wire EQ1, GT1;
    wire [1:0] A, B;
    // outputs of the module (wire)
    wire EQ0, GT0;
    // Instantiate the module to test
    comp_2 compare(.EQ1(EQ1), .GT1(GT1), .A(A), .B(B), .EQ0(EQ0), .GT0(GT0));

    /////// Input Initialization
    // Initialize the inputs and specify the runtime
    // initial begin
    //     // Initialize the inputs to 0
    //     GT1 = 1'b0;
    //     EQ1 = 1'b0;
    //     A = 2'b0;
    //     B = 2'b0;
    //     // Set a time delay, in nanoseconds
    //     #160;
    //     // Ends the testbench
    //     $finish;
    // end

    //////    Input Manipulation
    
    integer i;
    assign {GT1, EQ1, A, B} = i[5:0];

    initial begin

        for (i=0; i<64; i++) begin
            #20;
            $display("GT1:%b, EQ1:%b, A:%b, B:%b => GT0:%b, EQ0:%b", GT1, EQ1, A, B, GT0, EQ0);
        end

        $finish;
    end
    
    // //////  Output Results   //////
    // always @(GT1, EQ1, A, B, GT0, EQ0) begin
    //     // Small Delay so outputs can stabilize
    //     #1;
    //     $display("A:%b, B:%b, Cin:%b => S:%b, Cout:%b", A, B, Cin, S, Cout);

    // end

    // output waveform
    initial begin
        // output file name
        $dumpfile("comp_2.vcd");
        $dumpvars(0, comp_2_tb);
    end

endmodule

alu-main/lab3/comp_2.vcd
$date
	Tue Jan 28 15:22:57 2025
$end
$version
	Icarus Verilog
$end
$timescale
	100ps
$end
$scope module comp_2_tb $end
$var wire 1 ! GT1 $end
$var wire 1 " GT0 $end
$var wire 1 # EQ1 $end
$var wire 1 $ EQ0 $end
$var wire 2 % B [1:0] $end
$var wire 2 & A [1:0] $end
$var integer 32 ' i [31:0] $end
$scope module compare $end
$var wire 2 ( A [1:0] $end
$var wire 2 ) B [1:0] $end
$var wire 1 $ EQ0 $end
$var wire 1 # EQ1 $end
$var wire 1 " GT0 $end
$var wire 1 ! GT1 $end
$var wire 1 * zero $end
$var wire 3 + select [2:0] $end
$var wire 1 , one $end
$var wire 1 - gt_mux_out $end
$var wire 1 . eqmux_out $end
$scope module eqmux $end
$var wire 1 / in0 $end
$var wire 1 * in1 $end
$var wire 1 0 in2 $end
$var wire 1 * in3 $end
$var wire 1 * in4 $end
$var wire 1 1 in5 $end
$var wire 1 * in6 $end
$var wire 1 2 in7 $end
$var wire 3 3 select [2:0] $end
$var wire 1 4 w2 $end
$var wire 1 5 w1 $end
$var wire 1 . out $end
$scope module first_bottom $end
$var wire 1 * in0 $end
$var wire 1 1 in1 $end
$var wire 1 * in2 $end
$var wire 1 2 in3 $end
$var wire 2 6 select [1:0] $end
$var wire 1 7 w2 $end
$var wire 1 8 w1 $end
$var wire 1 4 out $end
$scope module first_bottom $end
$var wire 1 * in0 $end
$var wire 1 2 in1 $end
$var wire 1 9 select $end
$var wire 1 7 out $end
$upscope $end
$scope module first_top $end
$var wire 1 * in0 $end
$var wire 1 1 in1 $end
$var wire 1 : select $end
$var wire 1 8 out $end
$upscope $end
$scope module second $end
$var wire 1 8 in0 $end
$var wire 1 7 in1 $end
$var wire 1 ; select $end
$var wire 1 4 out $end
$upscope $end
$upscope $end
$scope module first_top $end
$var wire 1 / in0 $end
$var wire 1 * in1 $end
$var wire 1 0 in2 $end
$var wire 1 * in3 $end
$var wire 2 < select [1:0] $end
$var wire 1 = w2 $end
$var wire 1 > w1 $end
$var wire 1 5 out $end
$scope module first_bottom $end
$var wire 1 0 in0 $end
$var wire 1 * in1 $end
$var wire 1 ? select $end
$var wire 1 = out $end
$upscope $end
$scope module first_top $end
$var wire 1 / in0 $end
$var wire 1 * in1 $end
$var wire 1 @ select $end
$var wire 1 > out $end
$upscope $end
$scope module second $end
$var wire 1 > in0 $end
$var wire 1 = in1 $end
$var wire 1 A select $end
$var wire 1 5 out $end
$upscope $end
$upscope $end
$scope module second $end
$var wire 1 5 in0 $end
$var wire 1 4 in1 $end
$var wire 1 B select $end
$var wire 1 . out $end
$upscope $end
$upscope $end
$scope module gt_mux $end
$var wire 1 * in0 $end
$var wire 1 * in1 $end
$var wire 1 C in2 $end
$var wire 1 * in3 $end
$var wire 1 , in4 $end
$var wire 1 * in5 $end
$var wire 1 , in6 $end
$var wire 1 D in7 $end
$var wire 3 E select [2:0] $end
$var wire 1 F w2 $end
$var wire 1 G w1 $end
$var wire 1 - out $end
$scope module first_bottom $end
$var wire 1 , in0 $end
$var wire 1 * in1 $end
$var wire 1 , in2 $end
$var wire 1 D in3 $end
$var wire 2 H select [1:0] $end
$var wire 1 I w2 $end
$var wire 1 J w1 $end
$var wire 1 F out $end
$scope module first_bottom $end
$var wire 1 , in0 $end
$var wire 1 D in1 $end
$var wire 1 K select $end
$var wire 1 I out $end
$upscope $end
$scope module first_top $end
$var wire 1 , in0 $end
$var wire 1 * in1 $end
$var wire 1 L select $end
$var wire 1 J out $end
$upscope $end
$scope module second $end
$var wire 1 J in0 $end
$var wire 1 I in1 $end
$var wire 1 M select $end
$var wire 1 F out $end
$upscope $end
$upscope $end
$scope module first_top $end
$var wire 1 * in0 $end
$var wire 1 * in1 $end
$var wire 1 C in2 $end
$var wire 1 * in3 $end
$var wire 2 N select [1:0] $end
$var wire 1 O w2 $end
$var wire 1 P w1 $end
$var wire 1 G out $end
$scope module first_bottom $end
$var wire 1 C in0 $end
$var wire 1 * in1 $end
$var wire 1 Q select $end
$var wire 1 O out $end
$upscope $end
$scope module first_top $end
$var wire 1 * in0 $end
$var wire 1 * in1 $end
$var wire 1 R select $end
$var wire 1 P out $end
$upscope $end
$scope module second $end
$var wire 1 P in0 $end
$var wire 1 O in1 $end
$var wire 1 S select $end
$var wire 1 G out $end
$upscope $end
$upscope $end
$scope module second $end
$var wire 1 G in0 $end
$var wire 1 F in1 $end
$var wire 1 T select $end
$var wire 1 - out $end
$upscope $end
$upscope $end
$upscope $end
$upscope $end
$enddefinitions $end
$comment Show the parameter values. $end
$dumpall
$end
#0
$dumpvars
0T
0S
0R
0Q
0P
1O
b0 N
0M
0L
0K
1J
1I
b0 H
0G
1F
b0 E
1D
1C
0B
0A
0@
0?
1>
0=
b0 <
0;
0:
09
08
07
b0 6
15
04
b0 3
02
11
00
1/
1.
0-
1,
b0 +
0*
b0 )
b0 (
b0 '
b0 &
b0 %
0$
0#
0"
0!
$end
#200
0.
05
0>
1=
0O
0/
10
01
12
0C
0D
b1 %
b1 )
b1 '
#400
14
0F
18
0J
0.
1@
1?
1:
19
1R
1Q
1L
1K
05
b1 <
b1 6
b1 N
b1 H
0>
0=
0O
b1 +
b1 3
b1 E
1/
00
11
02
1C
1D
b10 %
b10 )
b10 '
#600
04
08
17
0I
0/
10
01
12
0C
0D
b11 %
b11 )
b11 '
#800
1"
1-
1G
1>
1O
1J
1F
0@
0?
1A
0:
09
1;
0R
0Q
1S
0L
0K
1M
08
07
1I
b10 <
b10 6
b10 N
b10 H
1/
00
11
02
1C
1D
b10 +
b10 3
b10 E
b0 %
b0 )
b1 &
b1 (
b100 '
#1000
0"
1.
0-
15
0G
0>
1=
0O
0/
10
01
12
0C
0D
b1 %
b1 )
b101 '
#1200
0"
18
0J
0.
0-
1@
1?
1:
19
1R
1Q
1L
1K
05
0G
b11 <
b11 6
b11 N
b11 H
0>
0=
0O
b11 +
b11 3
b11 E
1/
00
11
02
1C
1D
b10 %
b10 )
b110 '
#1400
14
0F
08
17
0I
0/
10
01
12
0C
0D
b11 %
b11 )
b111 '
#1600
1"
1-
15
04
1F
1>
1O
1J
0.
0@
0?
0A
0:
09
0;
0R
0Q
0S
0L
0K
0M
08
07
1I
1B
1T
b0 <
b0 6
b0 N
b0 H
1/
00
11
02
1C
1D
b100 +
b100 3
b100 E
b0 %
b0 )
b10 &
b10 (
b1000 '
#1800
05
0>
1=
0O
0/
10
01
12
0C
0D
b1 %
b1 )
b1001 '
#2000
0"
1.
0-
14
0F
18
0J
1@
1?
1:
19
1R
1Q
1L
1K
05
b1 <
b1 6
b1 N
b1 H
0>
0=
0O
b101 +
b101 3
b101 E
1/
00
11
02
1C
1D
b10 %
b10 )
b1010 '
#2200
0.
04
08
17
0I
0/
10
01
12
0C
0D
b11 %
b11 )
b1011 '
#2400
1"
1G
1-
1>
1O
1J
1F
0@
0?
1A
0:
09
1;
0R
0Q
1S
0L
0K
1M
08
07
1I
b10 <
b10 6
b10 N
b10 H
1/
00
11
02
1C
1D
b110 +
b110 3
b110 E
b0 %
b0 )
b11 &
b11 (
b1100 '
#2600
15
0G
0>
1=
0O
0/
10
01
12
0C
0D
b1 %
b1 )
b1101 '
#2800
18
0J
1@
1?
1:
19
1R
1Q
1L
1K
05
0G
b11 <
b11 6
b11 N
b11 H
0>
0=
0O
b111 +
b111 3
b111 E
1/
00
11
02
1C
1D
b10 %
b10 )
b1110 '
#3000
0"
1.
0-
14
0F
08
17
0I
0/
10
01
12
0C
0D
b11 %
b11 )
b1111 '
#3200
15
04
1F
1>
1O
1J
1.
0@
0?
0A
0:
09
0;
0R
0Q
0S
0L
0K
0M
08
07
1I
0B
0T
b0 <
b0 6
b0 N
b0 H
1/
00
11
02
1C
1D
b0 +
b0 3
b0 E
1$
b0 %
b0 )
b0 &
b0 (
1#
b10000 '
#3400
0$
0.
05
0>
1=
0O
0/
10
01
12
0C
0D
b1 %
b1 )
b10001 '
#3600
14
0F
0$
18
0J
0.
1@
1?
1:
19
1R
1Q
1L
1K
05
b1 <
b1 6
b1 N
b1 H
0>
0=
0O
b1 +
b1 3
b1 E
1/
00
11
02
1C
1D
b10 %
b10 )
b10010 '
#3800
04
08
17
0I
0/
10
01
12
0C
0D
b11 %
b11 )
b10011 '
#4000
1"
1-
1G
1>
1O
1J
1F
0@
0?
1A
0:
09
1;
0R
0Q
1S
0L
0K
1M
08
07
1I
b10 <
b10 6
b10 N
b10 H
1/
00
11
02
1C
1D
b10 +
b10 3
b10 E
b0 %
b0 )
b1 &
b1 (
b10100 '
#4200
1$
0"
1.
0-
15
0G
0>
1=
0O
0/
10
01
12
0C
0D
b1 %
b1 )
b10101 '
#4400
0$
0"
18
0J
0.
0-
1@
1?
1:
19
1R
1Q
1L
1K
05
0G
b11 <
b11 6
b11 N
b11 H
0>
0=
0O
b11 +
b11 3
b11 E
1/
00
11
02
1C
1D
b10 %
b10 )
b10110 '
#4600
14
0F
08
17
0I
0/
10
01
12
0C
0D
b11 %
b11 )
b10111 '
#4800
1"
1-
15
04
1F
0$
1>
1O
1J
0.
0@
0?
0A
0:
09
0;
0R
0Q
0S
0L
0K
0M
08
07
1I
1B
1T
b0 <
b0 6
b0 N
b0 H
1/
00
11
02
1C
1D
b100 +
b100 3
b100 E
b0 %
b0 )
b10 &
b10 (
b11000 '
#5000
05
0>
1=
0O
0/
10
01
12
0C
0D
b1 %
b1 )
b11001 '
#5200
1$
0"
1.
0-
14
0F
18
0J
1@
1?
1:
19
1R
1Q
1L
1K
05
b1 <
b1 6
b1 N
b1 H
0>
0=
0O
b101 +
b101 3
b101 E
1/
00
11
02
1C
1D
b10 %
b10 )
b11010 '
#5400
0$
0.
04
08
17
0I
0/
10
01
12
0C
0D
b11 %
b11 )
b11011 '
#5600
1"
1G
1-
1>
1O
1J
1F
0@
0?
1A
0:
09
1;
0R
0Q
1S
0L
0K
1M
08
07
1I
b10 <
b10 6
b10 N
b10 H
1/
00
11
02
1C
1D
b110 +
b110 3
b110 E
b0 %
b0 )
b11 &
b11 (
b11100 '
#5800
15
0G
0>
1=
0O
0/
10
01
12
0C
0D
b1 %
b1 )
b11101 '
#6000
18
0J
1@
1?
1:
19
1R
1Q
1L
1K
05
0G
b11 <
b11 6
b11 N
b11 H
0>
0=
0O
b111 +
b111 3
b111 E
1/
00
11
02
1C
1D
b10 %
b10 )
b11110 '
#6200
1$
0"
1.
0-
14
0F
08
17
0I
0/
10
01
12
0C
0D
b11 %
b11 )
b11111 '
#6400
15
04
1F
1>
1O
1J
1.
0@
0?
0A
0:
09
0;
0R
0Q
0S
0L
0K
0M
08
07
1I
0B
0T
b0 <
b0 6
b0 N
b0 H
1"
1/
00
11
02
1C
1D
b0 +
b0 3
b0 E
0$
b0 %
b0 )
b0 &
b0 (
0#
1!
b100000 '
#6600
0.
05
0>
1=
0O
0/
10
01
12
0C
0D
b1 %
b1 )
b100001 '
#6800
14
0F
18
0J
0.
1@
1?
1:
19
1R
1Q
1L
1K
05
b1 <
b1 6
b1 N
b1 H
0>
0=
0O
b1 +
b1 3
b1 E
1/
00
11
02
1C
1D
b10 %
b10 )
b100010 '
#7000
04
08
17
0I
0/
10
01
12
0C
0D
b11 %
b11 )
b100011 '
#7200
1-
1G
1>
1O
1J
1F
0@
0?
1A
0:
09
1;
0R
0Q
1S
0L
0K
1M
08
07
1I
b10 <
b10 6
b10 N
b10 H
1/
00
11
02
1C
1D
b10 +
b10 3
b10 E
b0 %
b0 )
b1 &
b1 (
b100100 '
#7400
1.
0-
15
0G
0>
1=
0O
0/
10
01
12
0C
0D
b1 %
b1 )
b100101 '
#7600
18
0J
0.
0-
1@
1?
1:
19
1R
1Q
1L
1K
05
0G
b11 <
b11 6
b11 N
b11 H
0>
0=
0O
b11 +
b11 3
b11 E
1/
00
11
02
1C
1D
b10 %
b10 )
b100110 '
#7800
14
0F
08
17
0I
0/
10
01
12
0C
0D
b11 %
b11 )
b100111 '
#8000
1-
15
04
1F
1>
1O
1J
0.
0@
0?
0A
0:
09
0;
0R
0Q
0S
0L
0K
0M
08
07
1I
1B
1T
b0 <
b0 6
b0 N
b0 H
1/
00
11
02
1C
1D
b100 +
b100 3
b100 E
b0 %
b0 )
b10 &
b10 (
b101000 '
#8200
05
0>
1=
0O
0/
10
01
12
0C
0D
b1 %
b1 )
b101001 '
#8400
1.
0-
14
0F
18
0J
1@
1?
1:
19
1R
1Q
1L
1K
05
b1 <
b1 6
b1 N
b1 H
0>
0=
0O
b101 +
b101 3
b101 E
1/
00
11
02
1C
1D
b10 %
b10 )
b101010 '
#8600
0.
04
08
17
0I
0/
10
01
12
0C
0D
b11 %
b11 )
b101011 '
#8800
1G
1-
1>
1O
1J
1F
0@
0?
1A
0:
09
1;
0R
0Q
1S
0L
0K
1M
08
07
1I
b10 <
b10 6
b10 N
b10 H
1/
00
11
02
1C
1D
b110 +
b110 3
b110 E
b0 %
b0 )
b11 &
b11 (
b101100 '
#9000
15
0G
0>
1=
0O
0/
10
01
12
0C
0D
b1 %
b1 )
b101101 '
#9200
18
0J
1@
1?
1:
19
1R
1Q
1L
1K
05
0G
b11 <
b11 6
b11 N
b11 H
0>
0=
0O
b111 +
b111 3
b111 E
1/
00
11
02
1C
1D
b10 %
b10 )
b101110 '
#9400
1.
0-
14
0F
08
17
0I
0/
10
01
12
0C
0D
b11 %
b11 )
b101111 '
#9600
15
04
1F
1>
1O
1J
1.
0@
0?
0A
0:
09
0;
0R
0Q
0S
0L
0K
0M
08
07
1I
0B
0T
b0 <
b0 6
b0 N
b0 H
0"
1/
00
11
02
1C
1D
b0 +
b0 3
b0 E
b0 %
b0 )
b0 &
b0 (
1#
b110000 '
#9800
0.
05
0>
1=
0O
0/
10
01
12
0C
0D
b1 %
b1 )
b110001 '
#10000
14
0F
18
0J
0.
1@
1?
1:
19
1R
1Q
1L
1K
05
b1 <
b1 6
b1 N
b1 H
0>
0=
0O
b1 +
b1 3
b1 E
1/
00
11
02
1C
1D
b10 %
b10 )
b110010 '
#10200
04
08
17
0I
0/
10
01
12
0C
0D
b11 %
b11 )
b110011 '
#10400
1"
1-
1G
1>
1O
1J
1F
0@
0?
1A
0:
09
1;
0R
0Q
1S
0L
0K
1M
08
07
1I
b10 <
b10 6
b10 N
b10 H
1/
00
11
02
1C
1D
b10 +
b10 3
b10 E
b0 %
b0 )
b1 &
b1 (
b110100 '
#10600
0"
1.
0-
15
0G
0>
1=
0O
0/
10
01
12
0C
0D
b1 %
b1 )
b110101 '
#10800
0"
18
0J
0.
0-
1@
1?
1:
19
1R
1Q
1L
1K
05
0G
b11 <
b11 6
b11 N
b11 H
0>
0=
0O
b11 +
b11 3
b11 E
1/
00
11
02
1C
1D
b10 %
b10 )
b110110 '
#11000
14
0F
08
17
0I
0/
10
01
12
0C
0D
b11 %
b11 )
b110111 '
#11200
1"
1-
15
04
1F
1>
1O
1J
0.
0@
0?
0A
0:
09
0;
0R
0Q
0S
0L
0K
0M
08
07
1I
1B
1T
b0 <
b0 6
b0 N
b0 H
1/
00
11
02
1C
1D
b100 +
b100 3
b100 E
b0 %
b0 )
b10 &
b10 (
b111000 '
#11400
05
0>
1=
0O
0/
10
01
12
0C
0D
b1 %
b1 )
b111001 '
#11600
0"
1.
0-
14
0F
18
0J
1@
1?
1:
19
1R
1Q
1L
1K
05
b1 <
b1 6
b1 N
b1 H
0>
0=
0O
b101 +
b101 3
b101 E
1/
00
11
02
1C
1D
b10 %
b10 )
b111010 '
#11800
0.
04
08
17
0I
0/
10
01
12
0C
0D
b11 %
b11 )
b111011 '
#12000
1"
1G
1-
1>
1O
1J
1F
0@
0?
1A
0:
09
1;
0R
0Q
1S
0L
0K
1M
08
07
1I
b10 <
b10 6
b10 N
b10 H
1/
00
11
02
1C
1D
b110 +
b110 3
b110 E
b0 %
b0 )
b11 &
b11 (
b111100 '
#12200
15
0G
0>
1=
0O
0/
10
01
12
0C
0D
b1 %
b1 )
b111101 '
#12400
18
0J
1@
1?
1:
19
1R
1Q
1L
1K
05
0G
b11 <
b11 6
b11 N
b11 H
0>
0=
0O
b111 +
b111 3
b111 E
1/
00
11
02
1C
1D
b10 %
b10 )
b111110 '
#12600
0"
1.
0-
14
0F
08
17
0I
0/
10
01
12
0C
0D
b11 %
b11 )
b111111 '
#12800
15
04
1F
1>
1O
1J
1.
0@
0?
0A
0:
09
0;
0R
0Q
0S
0L
0K
0M
08
07
1I
0B
0T
b0 <
b0 6
b0 N
b0 H
1/
00
11
02
1C
1D
b0 +
b0 3
b0 E
b0 %
b0 )
b0 &
b0 (
0#
0!
b1000000 '
